Metadata-Version: 1.0
Name: PratAgfirstpackage
Version: 0.1
Summary: firstpackage
Home-page: UNKNOWN
Author: UNKNOWN
Author-email: UNKNOWN
License: UNKNOWN
Platform: UNKNOWN
